hackers_kernels/__init__.py
hackers_kernels/kernels.py
hackers_kernels/ops.py
hackers_kernels/py.typed
hackers_kernels-0.1.6.dist-info/METADATA
hackers_kernels-0.1.6.dist-info/WHEEL
hackers_kernels-0.1.6.dist-info/RECORD
